rapid/__init__.py
rapid/process.py
rapid/settings.py
resto_api-0.0.2.dist-info/LICENSE.txt
resto_api-0.0.2.dist-info/METADATA
resto_api-0.0.2.dist-info/WHEEL
resto_api-0.0.2.dist-info/top_level.txt
resto_api-0.0.2.dist-info/RECORD
